odoo/addons/stock_product_pack/README.rst
odoo/addons/stock_product_pack/__init__.py
odoo/addons/stock_product_pack/__manifest__.py
odoo/addons/stock_product_pack/i18n/es.po
odoo/addons/stock_product_pack/i18n/pt.po
odoo/addons/stock_product_pack/i18n/stock_product_pack.pot
odoo/addons/stock_product_pack/models/__init__.py
odoo/addons/stock_product_pack/models/product_product.py
odoo/addons/stock_product_pack/readme/CONTRIBUTORS.rst
odoo/addons/stock_product_pack/readme/DESCRIPTION.rst
odoo/addons/stock_product_pack/readme/USAGE.rst
odoo/addons/stock_product_pack/static/description/icon.png
odoo/addons/stock_product_pack/static/description/index.html
odoo/addons/stock_product_pack/tests/__init__.py
odoo/addons/stock_product_pack/tests/test_stock_product_pack.py
odoo12_addon_stock_product_pack-12.0.1.0.1.dist-info/METADATA
odoo12_addon_stock_product_pack-12.0.1.0.1.dist-info/WHEEL
odoo12_addon_stock_product_pack-12.0.1.0.1.dist-info/top_level.txt
odoo12_addon_stock_product_pack-12.0.1.0.1.dist-info/RECORD
