Metadata-Version: 2.1
Name: odoo12-addon-stock-product-pack
Version: 12.0.1.0.1
Summary: This module allows you to get the right available quantities of the packs
Home-page: https://github.com/OCA/product-pack
Author: NaN·tic, ADHOC SA, Tecnativa, Odoo Community Association (OCA)
Author-email: support@odoo-community.org
License: AGPL-3
Platform: UNKNOWN
Classifier: Programming Language :: Python
Classifier: Framework :: Odoo
Classifier: License :: OSI Approved :: GNU Affero General Public License v3
Requires-Python: >=3.5
Requires-Dist: odoo12-addon-product-pack
Requires-Dist: odoo (<12.1dev,>=12.0a)
